geoenv/__init__.py
geoenv/commands/__init__.py
geoenv/commands/bash.py
geoenv/commands/core.py
geoenv/commands/jupyter_lab.py
geoenv/commands/postgres.py
geoenv/commands/update.py
geoenv/geoenv.py
geoenv_cli-0.1.5.dist-info/entry_points.txt
geoenv_cli-0.1.5.dist-info/LICENSE
geoenv_cli-0.1.5.dist-info/WHEEL
geoenv_cli-0.1.5.dist-info/METADATA
geoenv_cli-0.1.5.dist-info/RECORD
