Metadata-Version: 2.1
Name: geoenv-cli
Version: 0.1.5
Summary: GeoEnv is for those that don't want to create a geospatial development environment before you can test out some code you wrote, convert some spatial data or hack on an idea. The cli reduces the steps needed to spin up this working environment by using a docker image that already has a bunch of geospatial tools and libraries preloaded.
Home-page: https://github.com/gridcell/geoenv-cli
License: MIT
Author: Dustin Sampson
Author-email: gridcell@gmail.com
Requires-Python: >=3.7,<4.0
Classifier: License :: OSI Approved :: MIT License
Classifier: Programming Language :: Python :: 3
Classifier: Programming Language :: Python :: 3.10
Classifier: Programming Language :: Python :: 3.7
Classifier: Programming Language :: Python :: 3.8
Classifier: Programming Language :: Python :: 3.9
